tree_sitter_javascript/__init__.py
tree_sitter_javascript/__init__.pyi
tree_sitter_javascript/_binding.pyd
tree_sitter_javascript/binding.c
tree_sitter_javascript/py.typed
tree_sitter_javascript/queries/highlights-jsx.scm
tree_sitter_javascript/queries/highlights-params.scm
tree_sitter_javascript/queries/highlights.scm
tree_sitter_javascript/queries/injections.scm
tree_sitter_javascript/queries/locals.scm
tree_sitter_javascript/queries/tags.scm
tree_sitter_javascript-0.25.0.dist-info/licenses/LICENSE
tree_sitter_javascript-0.25.0.dist-info/METADATA
tree_sitter_javascript-0.25.0.dist-info/WHEEL
tree_sitter_javascript-0.25.0.dist-info/top_level.txt
tree_sitter_javascript-0.25.0.dist-info/RECORD
