Metadata-Version: 2.1
Name: tree-sitter-javascript
Version: 0.25.0
Summary: JavaScript grammar for tree-sitter
Author-email: Max Brunsfeld <maxbrunsfeld@gmail.com>, Amaan Qureshi <amaanq12@gmail.com>
License: MIT
Project-URL: Homepage, https://github.com/tree-sitter/tree-sitter-javascript
Keywords: incremental,parsing,tree-sitter,javascript
Classifier: Intended Audience :: Developers
Classifier: Topic :: Software Development :: Compilers
Classifier: Topic :: Text Processing :: Linguistic
Classifier: Typing :: Typed
Requires-Python: >=3.10
License-File: LICENSE
Provides-Extra: core
Requires-Dist: tree-sitter~=0.24; extra == "core"
